basictable/__init__.py
basictable/basictable.py
basictable-1.0.1.dist-info/LICENSE
basictable-1.0.1.dist-info/METADATA
basictable-1.0.1.dist-info/WHEEL
basictable-1.0.1.dist-info/top_level.txt
basictable-1.0.1.dist-info/RECORD
