Metadata-Version: 2.1
Name: basictable
Version: 1.0.1
Summary: A small library to print structured data tables
Home-page: https://github.com/Rich5/basictable
Author: Rich Kelley
Author-email: rk5devmail@gmail.com
License: UNKNOWN
Platform: UNKNOWN
Classifier: Programming Language :: Python :: 3
Classifier: License :: OSI Approved :: MIT License
Classifier: Operating System :: OS Independent
